{"trial_id": "0085", "hyperparameters": {"space": [{"class_name": "Int", "config": {"name": "units1", "default": null, "conditions": [], "min_value": 32, "max_value": 1024, "step": 32, "sampling": null}}, {"class_name": "Int", "config": {"name": "units2", "default": null, "conditions": [], "min_value": 32, "max_value": 1024, "step": 32, "sampling": null}}, {"class_name": "Int", "config": {"name": "units3", "default": null, "conditions": [], "min_value": 32, "max_value": 1024, "step": 32, "sampling": null}}, {"class_name": "Choice", "config": {"name": "learning_rate", "default": 0.01, "conditions": [], "values": [0.01, 0.001, 0.0001], "ordered": true}}], "values": {"units1": 64, "units2": 544, "units3": 864, "learning_rate": 0.0001, "tuner/epochs": 50, "tuner/initial_epoch": 0, "tuner/bracket": 0, "tuner/round": 0}}, "metrics": {"metrics": {"loss": {"direction": "min", "observations": [{"value": [0.6280223727226257], "step": 21}]}, "mae": {"direction": "min", "observations": [{"value": [0.4418257176876068], "step": 21}]}, "val_loss": {"direction": "min", "observations": [{"value": [0.5320838093757629], "step": 21}]}, "val_mae": {"direction": "min", "observations": [{"value": [0.35881465673446655], "step": 21}]}}}, "score": 0.35881465673446655, "best_step": 21, "status": "COMPLETED"}